keyctl/__init__.py
keyctl/key.py
keyctl/keyctlwrapper.py
keyctl/gui/__init__.py
keyctl/gui/_gui.py
keyctl/gui/addkey.ui
keyctl/gui/keylist.ui
keyctl/gui/main.py
keyctl-0.5.dist-info/LICENSE
keyctl-0.5.dist-info/METADATA
keyctl-0.5.dist-info/WHEEL
keyctl-0.5.dist-info/entry_points.txt
keyctl-0.5.dist-info/top_level.txt
keyctl-0.5.dist-info/RECORD
