Metadata-Version: 2.1
Name: keyctl
Version: 0.5
Summary: Wrapper to use keyctl command in Python
Author-email: Martin <tuxberlin@gmail.com>
Project-URL: repository, https://github.com/tuxberlin/python-keyctl
Project-URL: bug-tracker, https://github.com/tuxberlin/python-keyctl/issues
Classifier: Development Status :: 4 - Beta
Classifier: Intended Audience :: Developers
Classifier: License :: OSI Approved :: GNU General Public License v3 (GPLv3)
Classifier: Programming Language :: Python
Classifier: Programming Language :: Python :: 3.9
Classifier: Environment :: X11 Applications :: Qt
Classifier: Topic :: Utilities
Requires-Python: >=3.9
License-File: LICENSE
Provides-Extra: gui
Requires-Dist: PySide6 ; extra == 'gui'
